flask_html/__init__.py
flask_html/core.py
flask_html/tags.py
Flask_HTML-1.1.3.dist-info/LICENCE
Flask_HTML-1.1.3.dist-info/METADATA
Flask_HTML-1.1.3.dist-info/WHEEL
Flask_HTML-1.1.3.dist-info/top_level.txt
Flask_HTML-1.1.3.dist-info/RECORD
